BigEDA/EDA.py
BigEDA/__init__.py
BigEDA/descriptive.py
BigEDA/interactive_plots.py
BigEDA/plots.py
BigEDA/preprocessing.py
BigEDA-0.0.61.dist-info/LICENSE
BigEDA-0.0.61.dist-info/METADATA
BigEDA-0.0.61.dist-info/WHEEL
BigEDA-0.0.61.dist-info/top_level.txt
BigEDA-0.0.61.dist-info/RECORD
