Metadata-Version: 2.1
Name: BigEDA
Version: 0.0.61
Summary: This is a package to carry out Exploratory Data Analysis, allowing to work with Big Data.
Home-page: https://github.com/FabioScielzoOrtiz/EDA_Package
Author: Fabio Scielzo Ortiz
Author-email: fabioscielzo98@gmail.com
Classifier: Programming Language :: Python :: 3
Classifier: License :: OSI Approved :: MIT License
Classifier: Operating System :: OS Independent
Requires-Python: >=3.7
License-File: LICENSE
